condor_pytorch/__init__.py
condor_pytorch/activations.py
condor_pytorch/dataset.py
condor_pytorch/losses.py
condor_pytorch/metrics.py
condor_pytorch/version.py
condor_pytorch-1.1.0.dist-info/LICENSE.txt
condor_pytorch-1.1.0.dist-info/METADATA
condor_pytorch-1.1.0.dist-info/WHEEL
condor_pytorch-1.1.0.dist-info/top_level.txt
condor_pytorch-1.1.0.dist-info/RECORD
