Metadata-Version: 2.1
Name: condor-pytorch
Version: 1.1.0
Summary: A pytorch implementation of Conditionals for Ordinal Regression
Home-page: https://github.com/GarrettJenkinson/condor_pytorch
Author: Garrett Jenkinson
Author-email: Jenkinson.William@mayo.edu
License: UNKNOWN
Project-URL: Bug Tracker, https://github.com/GarrettJenkinson/condor_pytorch/issues
Platform: UNKNOWN
Classifier: Programming Language :: Python :: 3
Classifier: License :: OSI Approved :: MIT License
Classifier: Operating System :: OS Independent
Requires-Python: >=3.6
License-File: LICENSE.txt
